ryd_numerov/__init__.py
ryd_numerov/py.typed
ryd_numerov/rydberg.py
ryd_numerov/rydberg_mqdt.py
ryd_numerov/units.py
ryd_numerov/angular/__init__.py
ryd_numerov/angular/angular_matrix_element.py
ryd_numerov/angular/utils.py
ryd_numerov/elements/__init__.py
ryd_numerov/elements/base_element.py
ryd_numerov/elements/cesium.py
ryd_numerov/elements/hydrogen.py
ryd_numerov/elements/lithium.py
ryd_numerov/elements/potassium.py
ryd_numerov/elements/rubidium.py
ryd_numerov/elements/sodium.py
ryd_numerov/elements/strontium.py
ryd_numerov/elements/ytterbium.py
ryd_numerov/elements/nist_energy_levels/cesium.txt
ryd_numerov/elements/nist_energy_levels/lithium.txt
ryd_numerov/elements/nist_energy_levels/potassium.txt
ryd_numerov/elements/nist_energy_levels/rubidium.txt
ryd_numerov/elements/nist_energy_levels/sodium.txt
ryd_numerov/elements/nist_energy_levels/strontium.txt
ryd_numerov/elements/nist_energy_levels/ytterbium.txt
ryd_numerov/model/__init__.py
ryd_numerov/model/model.py
ryd_numerov/radial/__init__.py
ryd_numerov/radial/grid.py
ryd_numerov/radial/numerov.py
ryd_numerov/radial/radial_matrix_element.py
ryd_numerov/radial/wavefunction.py
ryd_numerov-0.8.1.dist-info/licenses/LICENSE.txt
ryd_numerov-0.8.1.dist-info/licenses/LICENSES/LGPL-3.0-or-later.txt
ryd_numerov-0.8.1.dist-info/METADATA
ryd_numerov-0.8.1.dist-info/WHEEL
ryd_numerov-0.8.1.dist-info/top_level.txt
ryd_numerov-0.8.1.dist-info/RECORD
