Metadata-Version: 2.4
Name: ryd-numerov
Version: 0.8.1
Summary: A Python package for calculating Rydberg wavefunctions.
Author: Rydberg Numerov Developers
Maintainer-email: Johannes Mögerle <johannes.moegerle@itp3.uni-stuttgart.de>
License-Expression: LGPL-3.0-or-later
Project-URL: Repository, https://github.com/pairinteraction/ryd-numerov
Keywords: rydberg,wavefunctions,numerov,quantum physics
Classifier: Development Status :: 4 - Beta
Classifier: Intended Audience :: Science/Research
Classifier: Operating System :: POSIX :: Linux
Classifier: Programming Language :: Python
Classifier: Programming Language :: Python :: 3
Classifier: Programming Language :: Python :: 3 :: Only
Classifier: Programming Language :: Python :: 3.9
Classifier: Programming Language :: Python :: 3.10
Classifier: Programming Language :: Python :: 3.11
Classifier: Programming Language :: Python :: 3.12
Classifier: Programming Language :: Python :: 3.13
Classifier: Topic :: Scientific/Engineering
Classifier: Topic :: Scientific/Engineering :: Physics
Classifier: Typing :: Typed
Requires-Python: >=3.9
License-File: LICENSE.txt
License-File: LICENSES/LGPL-3.0-or-later.txt
Requires-Dist: numpy>=2.0
Requires-Dist: numba>=0.60
Requires-Dist: pint>=0.24
Requires-Dist: scipy>=1.13
Requires-Dist: sympy>=1.13
Requires-Dist: mpmath>=1.3
Provides-Extra: tests
Requires-Dist: pytest>=8.0; extra == "tests"
Requires-Dist: nbmake>=1.3; extra == "tests"
Requires-Dist: ryd-numerov[benchmark]; extra == "tests"
Provides-Extra: docs
Requires-Dist: sphinx>=7; extra == "docs"
Requires-Dist: sphinx-rtd-theme>=2.0; extra == "docs"
Requires-Dist: nbsphinx>=0.9; extra == "docs"
Requires-Dist: nbconvert>=7.8; extra == "docs"
Requires-Dist: jupyter>=1.1; extra == "docs"
Requires-Dist: sphinx_autodoc_typehints>=1.24; extra == "docs"
Requires-Dist: sphinx-autobuild>=2021.3; extra == "docs"
Requires-Dist: matplotlib>=3.7.4; extra == "docs"
Requires-Dist: myst-parser>=3.0; extra == "docs"
Provides-Extra: benchmark
Requires-Dist: pairinteraction<1.0; extra == "benchmark"
Requires-Dist: arc-alkali-rydberg-calculator>=3.7.0; extra == "benchmark"
Provides-Extra: jupyter
Requires-Dist: pip; extra == "jupyter"
Requires-Dist: ipykernel; extra == "jupyter"
Provides-Extra: mypy
Requires-Dist: mypy>=1.14; extra == "mypy"
Requires-Dist: scipy-stubs>=1.15; python_version >= "3.10" and extra == "mypy"
Dynamic: license-file
